sphinx_pyscript.py
sphinx_pyscript-0.1.0.dist-info/LICENSE
sphinx_pyscript-0.1.0.dist-info/WHEEL
sphinx_pyscript-0.1.0.dist-info/METADATA
sphinx_pyscript-0.1.0.dist-info/RECORD
